{
    "name": "Hierarchy",
    "description": "everything gets better when there is only one leader",
    "iconPath": "assets/hierarchytech.png",

    "requiredIntelligence": 40,
    "intelligenceGain": 5,
    "duration": 5,

    "cost": {
      "food": 0,
      "materials": 0,
      "capacity": 0
    },
    
    "statBoosts": {
        "addends": {
            "huntBonus": 20,
            "gatheringBonus": 20,
            "fitnessGain": 0.5,
            "buildingBonus": 0,
            "birthGain": 0.7
        },
        "multipliers": {

        }
    }
}
